{
    "A->B": 10,
    "A->C": 15,
    "A->D": 20,
    "A->E": 25,
    "A->F": 30,
    "A->G": 35,
    "A->H": 40,
    "A->I": 45,
    "A->J": 50,
    "A->K": 55,
    "A->L": 60,
    "A->M": 65,
    "A->N": 70,
    "A->O": 75,
    "A->P": 80,
    "A->Q": 85,
    "A->R": 90,
    "A->S": 95,
    "A->T": 100,
    "A->U": 105,
    "A->V": 110,
    "A->W": 115,
    "A->X": 120,
    "A->Y": 125,
    "A->Z": 130,
    "B->C": 20,
    "B->D": 25,
    "B->E": 30,
    "B->F": 35,
    "B->G": 40,
    "B->H": 45,
    "B->I": 50,
    "B->J": 55,
    "B->K": 60,
    "B->L": 65,
    "B->M": 70,
    "B->N": 75,
    "B->O": 80,
    "B->P": 85,
    "B->Q": 90,
    "B->R": 95,
    "B->S": 100,
    "B->T": 105,
    "B->U": 110,
    "B->V": 115,
    "B->W": 120,
    "B->X": 125,
    "B->Y": 130,
    "B->Z": 135,
    "C->D": 30,
    "C->E": 35,
    "C->F": 40,
    "C->G": 45,
    "C->H": 50,
    "C->I": 55,
    "C->J": 60,
    "C->K": 65,
    "C->L": 70,
    "C->M": 75,
    "C->N": 80,
    "C->O": 85,
    "C->P": 90,
    "C->Q": 95,
    "C->R": 100,
    "C->S": 105,
    "C->T": 110,
    "C->U": 115,
    "C->V": 120,
    "C->W": 125,
    "C->X": 130,
    "C->Y": 135,
    "C->Z": 140,
    "D->E": 40,
    "D->F": 45,
    "D->G": 50,
    "D->H": 55,
    "D->I": 60,
    "D->J": 65,
    "D->K": 70,
    "D->L": 75,
    "D->M": 80,
    "D->N": 85,
    "D->O": 90,
    "D->P": 95,
    "D->Q": 100,
    "D->R": 105,
    "D->S": 110,
    "D->T": 115,
    "D->U": 120,
    "D->V": 125,
    "D->W": 130,
    "D->X": 135,
    "D->Y": 140,
    "D->Z": 145,
    "E->F": 50,
    "E->G": 55,
    "E->H": 60,
    "E->I": 65,
    "E->J": 70,
    "E->K": 75,
    "E->L": 80,
    "E->M": 85,
    "E->N": 90,
    "E->O": 95,
    "E->P": 100,
    "E->Q": 105,
    "E->R": 110,
    "E->S": 115,
    "E->T": 120,
    "E->U": 125,
    "E->V": 130,
    "E->W": 135,
    "E->X": 140,
    "E->Y": 145,
    "E->Z": 150,
    "F->G": 60,
    "F->H": 65,
    "F->I": 70,
    "F->J": 75,
    "F->K": 80,
    "F->L": 85,
    "F->M": 90,
    "F->N": 95,
    "F->O": 100,
    "F->P": 105,
    "F->Q": 110,
    "F->R": 115,
    "F->S": 120,
    "F->T": 125,
    "F->U": 130,
    "F->V": 135,
    "F->W": 140,
    "F->X": 145,
    "F->Y": 150,
    "F->Z": 155,
    "G->H": 70,
    "G->I": 75,
    "G->J": 80,
    "G->K": 85,
    "G->L": 90,
    "G->M": 95,
    "G->N": 100,
    "G->O": 105,
    "G->P": 110,
    "G->Q": 115,
    "G->R": 120,
    "G->S": 125,
    "G->T": 130,
    "G->U": 135,
    "G->V": 140,
    "G->W": 145,
    "G->X": 150,
    "G->Y": 155,
    "G->Z": 160,
    "H->I": 80,
    "H->J": 85,
    "H->K": 90,
    "H->L": 95,
    "H->M": 100,
    "H->N": 105,
    "H->O": 110,
    "H->P": 115,
    "H->Q": 120,
    "H->R": 125,
    "H->S": 130,
    "H->T": 135,
    "H->U": 140,
    "H->V": 145,
    "H->W": 150,
    "H->X": 155,
    "H->Y": 160,
    "H->Z": 165,
    "I->J": 90,
    "I->K": 95,
    "I->L": 100,
    "I->M": 105,
    "I->N": 110,
    "I->O": 115,
    "I->P": 120,
    "I->Q": 125,
    "I->R": 130,
    "I->S": 135,
    "I->T": 140,
    "I->U": 145,
    "I->V": 150,
    "I->W": 155,
    "I->X": 160,
    "I->Y": 165,
    "I->Z": 170,
    "J->K": 100,
    "J->L": 105,
    "J->M": 110,
    "J->N": 115,
    "J->O": 120,
    "J->P": 125,
    "J->Q": 130,
    "J->R": 135,
    "J->S": 140,
    "J->T": 145,
    "J->U": 150,
    "J->V": 155,
    "J->W": 160,
    "J->X": 165,
    "J->Y": 170,
    "J->Z": 175,
    "K->L": 110,
    "K->M": 115,
    "K->N": 120,
    "K->O": 125,
    "K->P": 130,
    "K->Q": 135,
    "K->R": 140,
    "K->S": 145,
    "K->T": 150,
    "K->U": 155,
    "K->V": 160,
    "K->W": 165,
    "K->X": 170,
    "K->Y": 175,
    "K->Z": 180,
    "L->M": 120,
    "L->N": 125,
    "L->O": 130,
    "L->P": 135,
    "L->Q": 140,
    "L->R": 145,
    "L->S": 150,
    "L->T": 155,
    "L->U": 160,
    "L->V": 165,
    "L->W": 170,
    "L->X": 175,
    "L->Y": 180,
    "L->Z": 185,
    "M->N": 130,
    "M->O": 135,
    "M->P": 140,
    "M->Q": 145,
    "M->R": 150,
    "M->S": 155,
    "M->T": 160,
    "M->U": 165,
    "M->V": 170,
    "M->W": 175,
    "M->X": 180,
    "M->Y": 185,
    "M->Z": 190,
    "N->O": 140,
    "N->P": 145,
    "N->Q": 150,
    "N->R": 155,
    "N->S": 160,
    "N->T": 165,
    "N->U": 170,
    "N->V": 175,
    "N->W": 180,
    "N->X": 185,
    "N->Y": 190,
    "N->Z": 195,
    "O->P": 150,
    "O->Q": 155,
    "O->R": 160,
    "O->S": 165,
    "O->T": 170,
    "O->U": 175,
    "O->V": 180,
    "O->W": 185,
    "O->X": 190,
    "O->Y": 195,
    "O->Z": 200,
    "P->Q": 160,
    "P->R": 165,
    "P->S": 170,
    "P->T": 175,
    "P->U": 180,
    "P->V": 185,
    "P->W": 190,
    "P->X": 195,
    "P->Y": 200,
    "P->Z": 205,
    "Q->R": 170,
    "Q->S": 175,
    "Q->T": 180,
    "Q->U": 185,
    "Q->V": 190,
    "Q->W": 195,
    "Q->X": 200,
    "Q->Y": 205,
    "Q->Z": 210,
    "R->S": 180,
    "R->T": 185,
    "R->U": 190,
    "R->V": 195,
    "R->W": 200,
    "R->X": 205,
    "R->Y": 210,
    "R->Z": 215,
    "S->T": 190,
    "S->U": 195,
    "S->V": 200,
    "S->W": 205,
    "S->X": 210,
    "S->Y": 215,
    "S->Z": 220,
    "T->U": 200,
    "T->V": 205,
    "T->W": 210,
    "T->X": 215,
    "T->Y": 220,
    "T->Z": 225,
    "U->V": 210,
    "U->W": 215,
    "U->X": 220,
    "U->Y": 225,
    "U->Z": 230,
    "V->W": 220,
    "V->X": 225,
    "V->Y": 230,
    "V->Z": 235,
    "W->X": 230,
    "W->Y": 235,
    "W->Z": 240,
    "X->Y": 240,
    "X->Z": 245,
    "Y->Z": 250
}